graphql_builder/__init__.py
graphql_builder/py.typed
graphql_builder/_internal/__init__.py
graphql_builder/_internal/build_state.py
graphql_builder/_internal/builders.py
graphql_builder/_internal/enums.py
graphql_builder/_internal/fields.py
graphql_builder/_internal/template.py
graphql_builder/_internal/typings.py
graphql_builder/_internal/utils.py
graphql_builder-1.0.0a3.dist-info/WHEEL
graphql_builder-1.0.0a3.dist-info/METADATA
graphql_builder-1.0.0a3.dist-info/RECORD
