Metadata-Version: 2.1
Name: graphql_builder
Version: 1.0.0a3
Summary: Easy solution for dynamic generation of GraphQL operations.
Author: Jakub Kuczys (jack1142)
Requires-Python: >=3.8
Classifier: Development Status :: 3 - Alpha
Classifier: Intended Audience :: Developers
Classifier: License :: OSI Approved :: Apache Software License
Classifier: Operating System :: OS Independent
Classifier: Programming Language :: Python :: 3.8
Classifier: Programming Language :: Python :: 3.9
Classifier: Topic :: Utilities
Classifier: Typing :: Typed
Requires-Dist: simplejson~=3.10
Requires-Dist: black==22.3.0 ; extra == "dev"
Requires-Dist: flake8==4.0.1 ; extra == "dev"
Requires-Dist: isort==5.10.1 ; extra == "dev"
Requires-Dist: mypy==0.961 ; extra == "dev"
Requires-Dist: types-simplejson==3.17.6 ; extra == "dev"
Project-URL: Documentation, https://graphql-builder.readthedocs.io
Project-URL: Issue Tracker, https://github.com/jack1142/graphql-builder/issues
Project-URL: Source Code, https://github.com/jack1142/graphql-builder
Project-URL: Sponsor on GitHub, https://github.com/sponsors/jack1142
Provides-Extra: dev
